Gelatin/__init__.py
Gelatin/util.py
Gelatin/version.py
Gelatin/compiler/Context.py
Gelatin/compiler/Function.py
Gelatin/compiler/Grammar.py
Gelatin/compiler/MatchFieldList.py
Gelatin/compiler/MatchList.py
Gelatin/compiler/MatchStatement.py
Gelatin/compiler/Number.py
Gelatin/compiler/Regex.py
Gelatin/compiler/SkipStatement.py
Gelatin/compiler/String.py
Gelatin/compiler/SyntaxCompiler.py
Gelatin/compiler/Token.py
Gelatin/compiler/WhenStatement.py
Gelatin/compiler/__init__.py
Gelatin/generator/Builder.py
Gelatin/generator/Dummy.py
Gelatin/generator/Json.py
Gelatin/generator/Xml.py
Gelatin/generator/Yaml.py
Gelatin/generator/__init__.py
Gelatin/parser/Dedent.py
Gelatin/parser/Indent.py
Gelatin/parser/Newline.py
Gelatin/parser/Parser.py
Gelatin/parser/Token.py
Gelatin/parser/__init__.py
Gelatin/parser/syntax.ebnf
Gelatin/parser/util.py
Gelatin-2.2.10.data/scripts/gel
Gelatin-2.2.10.dist-info/DESCRIPTION.rst
Gelatin-2.2.10.dist-info/METADATA
Gelatin-2.2.10.dist-info/RECORD
Gelatin-2.2.10.dist-info/WHEEL
Gelatin-2.2.10.dist-info/metadata.json
Gelatin-2.2.10.dist-info/top_level.txt
tests/__init__.py
tests/demo_test.py
